netbox_cloudflare_plugin/__init__.py
netbox_cloudflare_plugin/filtersets.py
netbox_cloudflare_plugin/forms.py
netbox_cloudflare_plugin/models.py
netbox_cloudflare_plugin/navigation.py
netbox_cloudflare_plugin/signals.py
netbox_cloudflare_plugin/tables.py
netbox_cloudflare_plugin/urls.py
netbox_cloudflare_plugin/views.py
netbox_cloudflare_plugin/api/__init__.py
netbox_cloudflare_plugin/api/serializers.py
netbox_cloudflare_plugin/api/urls.py
netbox_cloudflare_plugin/api/views.py
netbox_cloudflare_plugin/migrations/0001_initial.py
netbox_cloudflare_plugin/migrations/0002_alter_dnsrecord_record_id.py
netbox_cloudflare_plugin/migrations/0003_remove_dnsrecord_netbox_cloudflare_plugin_dnsrecord_unique_zone_name_type_content_and_more.py
netbox_cloudflare_plugin/migrations/__init__.py
netbox_cloudflare_plugin/templates/netbox_cloudflare_plugin/dnsrecord.html
netbox_cloudflare_plugin/templates/netbox_cloudflare_plugin/no_edit_base.html
netbox_cloudflare_plugin/templates/netbox_cloudflare_plugin/zoneaccount.html
netbox_cloudflare_plugin/tests/__init__.py
netbox_cloudflare_plugin/tests/base.py
netbox_cloudflare_plugin/tests/test_init.py
netbox_cloudflare_plugin/tests/dnsrecord/__init__.py
netbox_cloudflare_plugin/tests/dnsrecord/test_dnsrecord_api.py
netbox_cloudflare_plugin/tests/utilities/__init__.py
netbox_cloudflare_plugin/tests/utilities/test_cloudflare_dns_client.py
netbox_cloudflare_plugin/tests/zoneaccount/__init__.py
netbox_cloudflare_plugin/tests/zoneaccount/test_zoneaccount_api.py
netbox_cloudflare_plugin/utilities/__init__.py
netbox_cloudflare_plugin/utilities/cloudflare_dns_client.py
netbox_cloudflare_plugin-0.5.0.dist-info/licenses/LICENSE
netbox_cloudflare_plugin-0.5.0.dist-info/METADATA
netbox_cloudflare_plugin-0.5.0.dist-info/WHEEL
netbox_cloudflare_plugin-0.5.0.dist-info/top_level.txt
netbox_cloudflare_plugin-0.5.0.dist-info/RECORD
