Metadata-Version: 2.4
Name: netbox-cloudflare-plugin
Version: 0.5.0
Summary: Manage Cloudflare with Netbox & style.
Author-email: Vincent Simonin <vincent@saashup.com>
Project-URL: Homepage, https://github.com/SaaShup/netbox-cloudflare-plugin
Project-URL: Bug Tracker, https://github.com/SaaShup/netbox-cloudflare-plugin/issues
Keywords: netbox,netbox-plugin,cloudflare
Classifier: Programming Language :: Python :: 3
Requires-Python: >=3.12
License-File: LICENSE
Dynamic: license-file
